[
  {
    "op": "core/text-transform",
    "description": "Text transform on cells in column aroma using expression value.toNumber()",
    "engineConfig": {
      "facets": [],
      "mode": "row-based"
    },
    "columnName": "aroma",
    "expression": "value.toNumber()",
    "onError": "keep-original",
    "repeat": false,
    "repeatCount": 10
  },
  {
    "op": "core/text-transform",
    "description": "Text transform on cells in column flavor using expression value.toNumber()",
    "engineConfig": {
      "facets": [],
      "mode": "row-based"
    },
    "columnName": "flavor",
    "expression": "value.toNumber()",
    "onError": "keep-original",
    "repeat": false,
    "repeatCount": 10
  },
  {
    "op": "core/text-transform",
    "description": "Text transform on cells in column after using expression value.toNumber()",
    "engineConfig": {
      "facets": [],
      "mode": "row-based"
    },
    "columnName": "after",
    "expression": "value.toNumber()",
    "onError": "keep-original",
    "repeat": false,
    "repeatCount": 10
  },
  {
    "op": "core/text-transform",
    "description": "Text transform on cells in column acidity using expression value.toNumber()",
    "engineConfig": {
      "facets": [],
      "mode": "row-based"
    },
    "columnName": "acidity",
    "expression": "value.toNumber()",
    "onError": "keep-original",
    "repeat": false,
    "repeatCount": 10
  },
  {
    "op": "core/text-transform",
    "description": "Text transform on cells in column body using expression value.toNumber()",
    "engineConfig": {
      "facets": [],
      "mode": "row-based"
    },
    "columnName": "body",
    "expression": "value.toNumber()",
    "onError": "keep-original",
    "repeat": false,
    "repeatCount": 10
  },
  {
    "op": "core/text-transform",
    "description": "Text transform on cells in column mouthfeel using expression value.toNumber()",
    "engineConfig": {
      "facets": [],
      "mode": "row-based"
    },
    "columnName": "mouthfeel",
    "expression": "value.toNumber()",
    "onError": "keep-original",
    "repeat": false,
    "repeatCount": 10
  },
  {
    "op": "core/text-transform",
    "description": "Text transform on cells in column balance using expression value.toNumber()",
    "engineConfig": {
      "facets": [],
      "mode": "row-based"
    },
    "columnName": "balance",
    "expression": "value.toNumber()",
    "onError": "keep-original",
    "repeat": false,
    "repeatCount": 10
  },
  {
    "op": "core/text-transform",
    "description": "Text transform on cells in column uniformity using expression value.toNumber()",
    "engineConfig": {
      "facets": [],
      "mode": "row-based"
    },
    "columnName": "uniformity",
    "expression": "value.toNumber()",
    "onError": "keep-original",
    "repeat": false,
    "repeatCount": 10
  },
  {
    "op": "core/text-transform",
    "description": "Text transform on cells in column clean using expression value.toNumber()",
    "engineConfig": {
      "facets": [],
      "mode": "row-based"
    },
    "columnName": "clean",
    "expression": "value.toNumber()",
    "onError": "keep-original",
    "repeat": false,
    "repeatCount": 10
  },
  {
    "op": "core/text-transform",
    "description": "Text transform on cells in column sweet using expression value.toNumber()",
    "engineConfig": {
      "facets": [],
      "mode": "row-based"
    },
    "columnName": "sweet",
    "expression": "value.toNumber()",
    "onError": "keep-original",
    "repeat": false,
    "repeatCount": 10
  },
  {
    "op": "core/text-transform",
    "description": "Text transform on cells in column overall using expression value.toNumber()",
    "engineConfig": {
      "facets": [],
      "mode": "row-based"
    },
    "columnName": "overall",
    "expression": "value.toNumber()",
    "onError": "keep-original",
    "repeat": false,
    "repeatCount": 10
  },
  {
    "op": "core/text-transform",
    "description": "Text transform on cells in column total using expression value.toNumber()",
    "engineConfig": {
      "facets": [],
      "mode": "row-based"
    },
    "columnName": "total",
    "expression": "value.toNumber()",
    "onError": "keep-original",
    "repeat": false,
    "repeatCount": 10
  },
  {
    "op": "core/text-transform",
    "description": "Text transform on cells in column pass using expression value.toNumber()",
    "engineConfig": {
      "facets": [],
      "mode": "row-based"
    },
    "columnName": "pass",
    "expression": "value.toNumber()",
    "onError": "keep-original",
    "repeat": false,
    "repeatCount": 10
  },
  {
    "op": "core/text-transform",
    "description": "Text transform on cells in column random_id using expression value.toNumber()",
    "engineConfig": {
      "facets": [],
      "mode": "row-based"
    },
    "columnName": "random_id",
    "expression": "value.toNumber()",
    "onError": "keep-original",
    "repeat": false,
    "repeatCount": 10
  }
]